{
    "icon": "fas-space-shuttle",
    "fields": [
        "name",
        "operator",
        "access_simple",
        "website",
        "wikidata"
    ],
    "moreFields": [
        "email",
        "fax",
        "internet_access",
        "internet_access/fee",
        "internet_access/ssid",
        "phone"
    ],
    "geometry": [
        "area",
        "point"
    ],
    "tags": {
        "aeroway": "spaceport"
    },
    "terms": [
        "cosmodrome",
        "rocket launch center",
        "rocket launch complex",
        "rocket launch site",
        "rocket range",
        "space port"
    ],
    "name": "Spaceport"
}
