{
    "icon": "iD-highway-living-street",
    "fields": [
        "name",
        "oneway",
        "maxspeed",
        "lanes",
        "surface",
        "structure",
        "access"
    ],
    "moreFields": [
        "covered",
        "cycleway",
        "flood_prone",
        "junction_line",
        "lit",
        "maxheight",
        "maxweight_bridge",
        "oneway/bicycle",
        "smoothness",
        "trolley_wire",
        "width"
    ],
    "geometry": [
        "line"
    ],
    "tags": {
        "highway": "living_street"
    },
    "name": "Living Street"
}
