{
    "icon": "maki-art-gallery",
    "fields": [
        "name",
        "operator",
        "address",
        "building_area",
        "opening_hours",
        "opening_hours/covid19"
    ],
    "moreFields": [
        "email",
        "fax",
        "gnis/feature_id",
        "internet_access",
        "internet_access/fee",
        "internet_access/ssid",
        "payment_multi",
        "phone",
        "ref/vatin",
        "website",
        "wheelchair"
    ],
    "geometry": [
        "point",
        "area"
    ],
    "terms": [
        "art*",
        "exhibit*",
        "paint*",
        "photo*",
        "sculpt*"
    ],
    "tags": {
        "tourism": "gallery"
    },
    "name": "Art Gallery"
}
