{
    "icon": "temaki-money_hand",
    "fields": [
        "name",
        "brand",
        "address",
        "building_area",
        "payment_multi",
        "currency_multi"
    ],
    "moreFields": [
        "email",
        "fax",
        "level",
        "opening_hours",
        "opening_hours/covid19",
        "phone",
        "website",
        "wheelchair"
    ],
    "geometry": [
        "point",
        "area"
    ],
    "terms": [
        "money order",
        "check",
        "bill",
        "currency",
        "finance",
        "wire transfer",
        "cable",
        "person to person",
        "cash to cash",
        "exchange"
    ],
    "tags": {
        "amenity": "money_transfer"
    },
    "name": "Money Transfer Station"
}
